CredentialDatabase/__init__.py
CredentialDatabase/breachcompilation.py
CredentialDatabase/credential_file.py
CredentialDatabase/dbhandler.py
CredentialDatabase/exceptions.py
CredentialDatabase/breachcompilationrestapi/__init__.py
CredentialDatabase/breachcompilationrestapi/app.py
CredentialDatabase/breachcompilationrestapi/routes/__init__.py
CredentialDatabase/breachcompilationrestapi/routes/api.py
CredentialDatabase/breachcompilationrestapi/routes/router.py
CredentialDatabase/config/example.ini
CredentialDatabase/db/__init__.py
CredentialDatabase/db/connector.py
CredentialDatabase/db/context.py
CredentialDatabase/db/creator.py
CredentialDatabase/db/fetcher.py
CredentialDatabase/db/inserter.py
CredentialDatabase/db/sqlite.py
CredentialDatabase/scripts/BreachCompilationDatabase.py
CredentialDatabase/scripts/BreachCompilationDatabase_old.py
CredentialDatabase/scripts/PasswordDatabase.py
CredentialDatabase/scripts/__init__.py
CredentialDatabase/test/__init__.py
CredentialDatabase/test/db/__init__.py
CredentialDatabase/test/db/test_connector.py
CredentialDatabase/test/db/test_creator.py
CredentialDatabase/test/db/test_fetcher.py
CredentialDatabase/test/db/test_inserter.py
CredentialDatabase/test/utils/__init__.py
CredentialDatabase/test/utils/test_password.py
CredentialDatabase/utils/__init__.py
CredentialDatabase/utils/logger.py
CredentialDatabase/utils/password.py
etc/systemd/system/CredentialDatabase.service
CredentialDatabase-1.0.2.dist-info/LICENSE
CredentialDatabase-1.0.2.dist-info/METADATA
CredentialDatabase-1.0.2.dist-info/WHEEL
CredentialDatabase-1.0.2.dist-info/entry_points.txt
CredentialDatabase-1.0.2.dist-info/top_level.txt
CredentialDatabase-1.0.2.dist-info/RECORD
