Metadata-Version: 2.1
Name: CredentialDatabase
Version: 1.0.2
Summary: creates a massive credential database
Home-page: https://github.com/bierschi/CredentialDatabase
Author: Christian Bierschneider
Author-email: christian.bierschneider@web.de
License: MIT
Keywords: PasswordDatabase,BreachCompilation,credentials,leaked,database,CredentialDatabase
Platform: UNKNOWN
Classifier: Development Status :: 5 - Production/Stable
Classifier: Intended Audience :: Developers
Classifier: Intended Audience :: End Users/Desktop
Classifier: License :: OSI Approved :: MIT License
Classifier: Operating System :: OS Independent
Classifier: Programming Language :: Python
Classifier: Programming Language :: Python :: 3
Classifier: Programming Language :: Python :: 3.3
Classifier: Programming Language :: Python :: 3.4
Classifier: Programming Language :: Python :: 3.5
Classifier: Programming Language :: Python :: 3.6
Classifier: Programming Language :: Python :: Implementation :: PyPy
Requires-Python: >=3
Requires-Dist: flask (>=1.1.1)
Requires-Dist: psycopg2 (>=2.8.3)
